ymhandler/__init__.py
ymhandler/main.py
ymhandler/parser.py
ymhandler/requester.py
YmHandler-1.14.1.dist-info/LICENSE
YmHandler-1.14.1.dist-info/METADATA
YmHandler-1.14.1.dist-info/WHEEL
YmHandler-1.14.1.dist-info/entry_points.txt
YmHandler-1.14.1.dist-info/top_level.txt
YmHandler-1.14.1.dist-info/RECORD
